{
    "os": "Linux-5.15.0-1064-azure-x86_64-with-glibc2.10",
    "python": "3.8.5",
    "heartbeatAt": "2024-06-01T17:11:43.232448",
    "startedAt": "2024-06-01T17:11:41.756249",
    "docker": null,
    "cuda": null,
    "args": [],
    "state": "running",
    "program": "/home/xnmaster/testproject/XNAPproject-grup-04/Cod-SoloBleu.py",
    "codePathLocal": "Cod-SoloBleu.py",
    "codePath": "Cod-SoloBleu.py",
    "git": {
        "remote": "https://github.com/DCC-UAB/XNAPproject-grup-04.git",
        "commit": "d30748b970c1d4dcb7664bccce7e129f7523d458"
    },
    "email": "1566320@uab.cat",
    "root": "/home/xnmaster/testproject/XNAPproject-grup-04",
    "host": "labDAGLBU",
    "username": "xnmaster",
    "executable": "/anaconda/envs/azureml_py38_PT_and_TF/bin/python",
    "cpu_count": 6,
    "cpu_count_logical": 6,
    "cpu_freq": {
        "current": 2593.993,
        "min": 0.0,
        "max": 0.0
    },
    "cpu_freq_per_core": [
        {
            "current": 2593.993,
            "min": 0.0,
            "max": 0.0
        },
        {
            "current": 2593.993,
            "min": 0.0,
            "max": 0.0
        },
        {
            "current": 2593.993,
            "min": 0.0,
            "max": 0.0
        },
        {
            "current": 2593.993,
            "min": 0.0,
            "max": 0.0
        },
        {
            "current": 2593.993,
            "min": 0.0,
            "max": 0.0
        },
        {
            "current": 2593.993,
            "min": 0.0,
            "max": 0.0
        }
    ],
    "disk": {
        "/": {
            "total": 145.1909637451172,
            "used": 90.96035766601562
        }
    },
    "gpu": "Tesla V100-PCIE-16GB",
    "gpu_count": 1,
    "gpu_devices": [
        {
            "name": "Tesla V100-PCIE-16GB",
            "memory_total": 16945512448
        }
    ],
    "memory": {
        "total": 110.04522323608398
    }
}
